{
    "homepage": "https://www.aardio.com/",
    "description": "A Windows desktop rapid programming platform",
    "version": "40.31.7",
    "license": "freeware",
    "url": "https://d.aardio.com/ide/aardio.7z",
    "hash": "0c00992290d80a7494c02b9657ef9d783a2011d3d3c53c62286bba1feb23db16",
    "bin": "aardio.exe",
    "shortcuts": [
        [
            "aardio.exe",
            "aardio"
        ]
    ],
    "persist": "config\\USR.CFG",
    "checkver": {
        "url": "https://ide.update.aardio.com/log/",
        "regex": "aardio v([\\d.]+)"
    },
    "autoupdate": {
        "url": "https://d.aardio.com/ide/aardio.7z"
    }
}
